generatepass/__init__.py
generatepass/ht_pass.py
generatepass-1.0.dist-info/METADATA
generatepass-1.0.dist-info/WHEEL
generatepass-1.0.dist-info/top_level.txt
generatepass-1.0.dist-info/RECORD
