Metadata-Version: 2.1
Name: generatepass
Version: 1.0
Summary: Password generator tools for project apps
Home-page: UNKNOWN
Author: RAKOTONIAINA Harry Yves
Author-email: iharrysh.rakotoniaina@gmail.com
License: @H._T Free
Platform: UNKNOWN
Classifier: Development Status :: 3 - Alpha
Classifier: Intended Audience :: Developers
Classifier: Programming Language :: Python :: 3.10
Classifier: Programming Language :: Python :: 3.11
Classifier: Topic :: Utilities
Requires-Python: >=3.10, <3.12
Requires-Dist: getpass
Requires-Dist: stringrandom
